autogluon.timeseries-1.4.0-py3.9-nspkg.pth
autogluon/timeseries/__init__.py
autogluon/timeseries/evaluator.py
autogluon/timeseries/learner.py
autogluon/timeseries/predictor.py
autogluon/timeseries/regressor.py
autogluon/timeseries/splitter.py
autogluon/timeseries/trainer.py
autogluon/timeseries/version.py
autogluon/timeseries/configs/__init__.py
autogluon/timeseries/configs/presets_configs.py
autogluon/timeseries/dataset/__init__.py
autogluon/timeseries/dataset/ts_dataframe.py
autogluon/timeseries/metrics/__init__.py
autogluon/timeseries/metrics/abstract.py
autogluon/timeseries/metrics/point.py
autogluon/timeseries/metrics/quantile.py
autogluon/timeseries/metrics/utils.py
autogluon/timeseries/models/__init__.py
autogluon/timeseries/models/presets.py
autogluon/timeseries/models/abstract/__init__.py
autogluon/timeseries/models/abstract/abstract_timeseries_model.py
autogluon/timeseries/models/abstract/model_trial.py
autogluon/timeseries/models/abstract/tunable.py
autogluon/timeseries/models/autogluon_tabular/__init__.py
autogluon/timeseries/models/autogluon_tabular/mlforecast.py
autogluon/timeseries/models/autogluon_tabular/per_step.py
autogluon/timeseries/models/autogluon_tabular/transforms.py
autogluon/timeseries/models/autogluon_tabular/utils.py
autogluon/timeseries/models/chronos/__init__.py
autogluon/timeseries/models/chronos/model.py
autogluon/timeseries/models/chronos/pipeline/__init__.py
autogluon/timeseries/models/chronos/pipeline/base.py
autogluon/timeseries/models/chronos/pipeline/chronos.py
autogluon/timeseries/models/chronos/pipeline/chronos_bolt.py
autogluon/timeseries/models/chronos/pipeline/utils.py
autogluon/timeseries/models/ensemble/__init__.py
autogluon/timeseries/models/ensemble/abstract.py
autogluon/timeseries/models/ensemble/basic.py
autogluon/timeseries/models/ensemble/greedy.py
autogluon/timeseries/models/gluonts/__init__.py
autogluon/timeseries/models/gluonts/abstract.py
autogluon/timeseries/models/gluonts/dataset.py
autogluon.timeseries-1.4.0.dist-info/LICENSE
autogluon.timeseries-1.4.0.dist-info/METADATA
autogluon.timeseries-1.4.0.dist-info/NOTICE
autogluon.timeseries-1.4.0.dist-info/WHEEL
autogluon.timeseries-1.4.0.dist-info/namespace_packages.txt
autogluon.timeseries-1.4.0.dist-info/top_level.txt
autogluon.timeseries-1.4.0.dist-info/zip-safe
autogluon.timeseries-1.4.0.dist-info/RECORD
