Metadata-Version: 2.1
Name: autogluon.timeseries
Version: 1.4.0
Summary: Fast and Accurate ML in 3 Lines of Code
Home-page: https://github.com/autogluon/autogluon
Author: AutoGluon Community
License: Apache-2.0
Project-URL: Documentation, https://auto.gluon.ai
Project-URL: Bug Reports, https://github.com/autogluon/autogluon/issues
Project-URL: Source, https://github.com/autogluon/autogluon/
Project-URL: Contribute!, https://github.com/autogluon/autogluon/blob/master/CONTRIBUTING.md
Platform: UNKNOWN
Classifier: Development Status :: 5 - Production/Stable
Classifier: Intended Audience :: Education
Classifier: Intended Audience :: Developers
Classifier: Intended Audience :: Science/Research
Classifier: Intended Audience :: Customer Service
Classifier: Intended Audience :: Financial and Insurance Industry
Classifier: Intended Audience :: Healthcare Industry
Classifier: Intended Audience :: Telecommunications Industry
Classifier: License :: OSI Approved :: Apache Software License
Classifier: Operating System :: MacOS
Classifier: Operating System :: Microsoft :: Windows
Classifier: Operating System :: POSIX
Classifier: Operating System :: Unix
Classifier: Programming Language :: Python :: 3
Classifier: Programming Language :: Python :: 3.9
Classifier: Programming Language :: Python :: 3.10
Classifier: Programming Language :: Python :: 3.11
Classifier: Programming Language :: Python :: 3.12
Classifier: Topic :: Software Development
Classifier: Topic :: Scientific/Engineering :: Artificial Intelligence
Classifier: Topic :: Scientific/Engineering :: Information Analysis
Classifier: Topic :: Scientific/Engineering :: Image Recognition
Requires-Python: >=3.9, <3.13
License-File: ../LICENSE
License-File: ../NOTICE
Requires-Dist: joblib<1.7,>=1.2
Requires-Dist: numpy<2.4.0,>=1.25.0
Requires-Dist: scipy<1.17,>=1.5.4
Requires-Dist: pandas<2.4.0,>=2.0.0
Requires-Dist: torch<2.8,>=2.2
Requires-Dist: lightning<2.8,>=2.2
Requires-Dist: pytorch-lightning
Requires-Dist: transformers[sentencepiece]<4.50,>=4.38.0
Requires-Dist: accelerate<2.0,>=0.34.0
Requires-Dist: gluonts<0.17,>=0.15.0
Requires-Dist: networkx<4,>=3.0
Requires-Dist: statsforecast<2.0.2,>=1.7.0
Requires-Dist: mlforecast<0.15.0,>=0.14.0
Requires-Dist: utilsforecast<0.2.12,>=0.2.3
Requires-Dist: coreforecast<0.0.17,>=0.0.12
Requires-Dist: fugue>=0.9.0
Requires-Dist: tqdm<5,>=4.38
Requires-Dist: orjson~=3.9
Requires-Dist: tensorboard<3,>=2.9
Requires-Dist: autogluon.core[raytune]==1.4.0
Requires-Dist: autogluon.common==1.4.0
Requires-Dist: autogluon.features==1.4.0
Requires-Dist: autogluon.tabular[catboost,lightgbm,xgboost]==1.4.0
Provides-Extra: all
Provides-Extra: tests
Requires-Dist: pytest; extra == "tests"
Requires-Dist: ruff>=0.0.285; extra == "tests"
Requires-Dist: flaky<4,>=3.7; extra == "tests"
Requires-Dist: pytest-timeout<3,>=2.1; extra == "tests"
